LICENSE
README.md
setup.py
scryptlib/__init__.py
scryptlib/abi.py
scryptlib/compiler_wrapper.py
scryptlib/contract.py
scryptlib/serializer.py
scryptlib/types.py
scryptlib/utils.py
scryptlib.egg-info/PKG-INFO
scryptlib.egg-info/SOURCES.txt
scryptlib.egg-info/dependency_links.txt
scryptlib.egg-info/requires.txt
scryptlib.egg-info/top_level.txt
test/test_contract_ackermann.py
test/test_contract_acs.py
test/test_contract_advanced_counter.py
test/test_contract_advanced_token_sale.py
test/test_contract_alias.py
test/test_contract_arraydemo.py
test/test_contract_asm.py
test/test_contract_clone.py
test/test_contract_conwaygol.py
test/test_contract_counter.py
test/test_contract_demo.py
test/test_contract_dynamic_array_demo.py
test/test_contract_ec_addition.py
test/test_contract_equals.py
test/test_contract_escrow.py
test/test_contract_faucet.py
test/test_contract_hashpuzzle.py
test/test_contract_matrix.py
test/test_contract_merkle_token.py
test/test_contract_mod_exp.py
test/test_contract_multisig.py
test/test_contract_nested_struct_arr.py
test/test_contract_non_fungible_token.py
test/test_contract_optimal_push_tx.py
test/test_contract_p2generic_ecdsa_pubkey.py
test/test_contract_p2pkh.py
test/test_contract_p2sh.py
test/test_contract_rabin.py
test/test_contract_rps.py
test/test_contract_rpuzzle.py
test/test_contract_secp256k1.py
test/test_contract_serializer.py
test/test_contract_simpleBVM.py
test/test_contract_state_counter.py
test/test_contract_state_map.py
test/test_contract_state_struct.py
test/test_contract_structdemo.py
test/test_contract_test_merkle_tree.py
test/test_contract_token.py
test/test_contract_token_manual_state.py
test/test_contract_token_sale.py
test/test_contract_token_utxo.py
test/test_multi_contract.py
test/test_optimized_compilation.py
test/test_types.py
test/test_utils.py