Metadata-Version: 2.1
Name: scryptlib
Version: 0.4.7
Summary: Python SDK for integration of sCrypt Bitcoin SV smart contracts.
Home-page: https://www.github.com/sCrypt-Inc/py-scryptlib
Author: Kala
License: UNKNOWN
Keywords: scrypt scryptlib bitcoin bsv blockchain
Platform: UNKNOWN
Requires-Python: >=3.7
Provides-Extra: testing
License-File: LICENSE
